{
	"name": "Samus (Power Suit)",
	"id": "samus-power-suit",
	"author": "BloodSweatAndCode",
	"description": "Samus in full gear",
	"spriteMaker": true,
	"patch": [
		{
			"offset": 135216,
			"bytes": [
				0,
				0,
				0,
				25,
				58,
				57,
				49,
				3,
				3,
				15,
				31,
				22,
				37,
				6,
				15,
				62,
				1,
				7,
				1,
				124,
				254,
				255,
				127,
				1,
				31,
				3,
				7,
				39,
				7,
				2,
				33,
				0,
				0,
				0,
				32,
				16,
				0,
				0,
				232,
				252,
				128,
				224,
				240,
				248,
				248,
				248,
				240,
				232,
				254,
				249,
				249,
				254,
				124,
				248,
				240,
				240,
				108,
				182,
				182,
				180,
				240,
				240,
				224,
				224
			]
		},
		{
			"offset": 135280,
			"bytes": [
				1,
				3,
				7,
				15,
				31,
				14,
				28,
				60,
				0,
				1,
				3,
				7,
				14,
				60,
				56,
				24,
				60,
				12,
				4,
				0,
				16,
				8,
				8,
				0,
				24,
				24,
				30,
				30,
				46,
				118,
				244,
				0,
				248,
				248,
				248,
				240,
				248,
				248,
				124,
				28,
				240,
				240,
				240,
				96,
				112,
				112,
				56,
				56,
				12,
				28,
				4,
				0,
				12,
				2,
				0,
				0,
				62,
				14,
				15,
				15,
				3,
				28,
				60,
				0
			]
		},
		{
			"offset": 135344,
			"bytes": [
				0,
				0,
				0,
				100,
				232,
				228,
				143,
				7,
				14,
				63,
				127,
				91,
				151,
				27,
				127,
				255,
				31,
				31,
				31,
				15,
				63,
				127,
				127,
				63,
				105,
				13,
				14,
				6,
				17,
				3,
				1,
				16,
				0,
				0,
				128,
				64,
				0,
				0,
				128,
				192,
				0,
				128,
				192,
				224,
				224,
				224,
				192,
				128,
				224,
				224,
				16,
				16,
				240,
				224,
				224,
				224,
				192,
				192,
				224,
				224,
				192,
				192,
				0,
				192
			]
		},
		{
			"offset": 135408,
			"bytes": [
				15,
				15,
				31,
				31,
				15,
				7,
				9,
				1,
				7,
				7,
				11,
				11,
				27,
				27,
				7,
				7,
				7,
				1,
				0,
				0,
				1,
				0,
				0,
				0,
				3,
				3,
				1,
				1,
				2,
				7,
				15,
				0,
				224,
				224,
				192,
				128,
				128,
				128,
				128,
				128,
				192,
				192,
				128,
				0,
				0,
				0,
				0,
				0,
				192,
				128,
				128,
				0,
				0,
				128,
				128,
				0,
				128,
				192,
				224,
				240,
				240,
				96,
				64,
				0
			]
		},
		{
			"offset": 135472,
			"bytes": [
				0,
				0,
				0,
				100,
				232,
				228,
				195,
				15,
				14,
				63,
				127,
				91,
				151,
				27,
				63,
				255,
				7,
				31,
				63,
				111,
				159,
				135,
				147,
				99,
				127,
				15,
				15,
				55,
				119,
				115,
				97,
				1,
				0,
				0,
				128,
				64,
				0,
				0,
				176,
				248,
				0,
				128,
				192,
				224,
				224,
				224,
				192,
				240,
				252,
				250,
				241,
				243,
				255,
				255,
				254,
				252,
				120,
				188,
				222,
				206,
				166,
				6,
				0,
				160
			]
		},
		{
			"offset": 135536,
			"bytes": [
				3,
				7,
				7,
				15,
				31,
				31,
				14,
				14,
				1,
				3,
				3,
				7,
				14,
				14,
				60,
				60,
				62,
				62,
				12,
				4,
				16,
				8,
				8,
				0,
				28,
				28,
				30,
				30,
				46,
				118,
				244,
				0,
				252,
				252,
				248,
				248,
				120,
				120,
				120,
				60,
				216,
				248,
				240,
				112,
				48,
				48,
				48,
				24,
				14,
				15,
				14,
				2,
				4,
				2,
				2,
				0,
				60,
				28,
				7,
				7,
				11,
				29,
				61,
				0
			]
		},
		{
			"offset": 135600,
			"bytes": [
				63,
				63,
				255,
				63,
				23,
				37,
				16,
				16,
				65,
				254,
				124,
				241,
				123,
				27,
				111,
				239
			]
		},
		{
			"offset": 135616,
			"bytes": [
				0,
				0,
				0,
				0,
				0,
				0,
				0,
				0,
				0,
				0,
				0,
				0,
				0,
				0,
				0,
				0
			]
		},
		{
			"offset": 135632,
			"bytes": [
				248,
				248,
				252,
				248,
				240,
				248,
				100,
				96,
				240,
				240,
				242,
				231,
				207,
				255,
				251,
				135
			]
		},
		{
			"offset": 135648,
			"bytes": [
				0,
				0,
				0,
				0,
				0,
				0,
				0,
				0,
				0,
				0,
				0,
				0,
				0,
				0,
				0,
				0
			]
		},
		{
			"offset": 135664,
			"bytes": [
				7,
				15,
				31,
				31,
				63,
				62,
				28,
				24,
				3,
				7,
				15,
				14,
				30,
				29,
				121,
				112,
				120,
				60,
				60,
				24,
				8,
				32,
				16,
				16,
				48,
				24,
				24,
				60,
				60,
				30,
				110,
				232
			]
		},
		{
			"offset": 135696,
			"bytes": [
				63,
				63,
				255,
				95,
				8,
				16,
				8,
				8,
				64,
				255,
				127,
				56,
				60,
				14,
				54,
				118,
				0,
				0,
				0,
				0,
				0,
				0,
				0,
				0,
				0,
				0,
				0,
				0,
				0,
				0,
				0,
				0,
				248,
				248,
				248,
				240,
				240,
				248,
				56,
				56,
				240,
				240,
				112,
				96,
				96,
				112,
				240,
				240,
				120,
				124,
				92,
				8,
				0,
				32,
				16,
				16,
				48,
				56,
				56,
				60,
				60,
				30,
				110,
				232
			]
		},
		{
			"offset": 135760,
			"bytes": [
				0,
				0,
				0,
				25,
				58,
				57,
				48,
				1,
				3,
				15,
				31,
				22,
				37,
				6,
				15,
				63,
				111,
				255,
				255,
				255,
				255,
				254,
				252,
				252,
				29,
				93,
				61,
				126,
				124,
				120,
				120,
				248,
				0,
				0,
				32,
				16,
				0,
				0,
				0,
				135,
				128,
				224,
				240,
				248,
				248,
				248,
				240,
				224,
				207,
				239,
				159,
				158,
				222,
				124,
				0,
				0,
				132,
				192,
				225,
				248,
				60,
				0,
				0,
				0
			]
		},
		{
			"offset": 135888,
			"bytes": [
				0,
				0,
				0,
				100,
				232,
				228,
				193,
				7,
				14,
				63,
				127,
				91,
				151,
				27,
				62,
				252,
				15,
				255,
				255,
				254,
				246,
				250,
				252,
				252,
				112,
				97,
				96,
				104,
				108,
				116,
				120,
				248,
				0,
				0,
				128,
				64,
				0,
				0,
				252,
				255,
				0,
				128,
				192,
				224,
				224,
				224,
				0,
				252,
				255,
				3,
				0,
				0,
				0,
				0,
				0,
				0,
				3,
				0,
				0,
				0,
				0,
				0,
				0,
				0
			]
		},
		{
			"offset": 135984,
			"bytes": [
				0,
				0,
				0,
				12,
				29,
				28,
				24,
				31,
				1,
				7,
				15,
				11,
				18,
				3,
				7,
				0,
				63,
				127,
				191,
				23,
				163,
				193,
				129,
				1,
				31,
				61,
				113,
				227,
				193,
				128,
				0,
				0,
				0,
				0,
				16,
				136,
				0,
				128,
				124,
				254,
				192,
				240,
				248,
				124,
				252,
				124,
				128,
				108,
				254,
				251,
				249,
				255,
				254,
				248,
				248,
				248,
				244,
				244,
				246,
				246,
				240,
				240,
				240,
				240
			]
		},
		{
			"offset": 136064,
			"bytes": [
				0,
				0,
				0,
				31,
				63,
				63,
				31,
				0,
				0,
				0,
				0,
				8,
				1,
				0,
				8,
				0
			]
		},
		{
			"offset": 136144,
			"bytes": [
				0,
				0,
				4,
				8,
				0,
				16,
				41,
				3,
				0,
				0,
				30,
				63,
				127,
				111,
				215,
				255,
				115,
				123,
				58,
				4,
				62,
				127,
				127,
				63,
				143,
				71,
				37,
				3,
				19,
				3,
				2,
				17,
				0,
				0,
				0,
				0,
				0,
				48,
				248,
				252,
				0,
				0,
				0,
				0,
				128,
				128,
				16,
				232,
				250,
				250,
				254,
				126,
				122,
				250,
				252,
				240,
				116,
				180,
				180,
				180,
				180,
				116,
				224,
				224
			]
		},
		{
			"offset": 136208,
			"bytes": [
				0,
				0,
				0,
				0,
				0,
				0,
				16,
				32,
				0,
				0,
				0,
				0,
				0,
				28,
				62,
				127,
				1,
				1,
				21,
				9,
				0,
				28,
				30,
				14,
				126,
				254,
				234,
				246,
				127,
				99,
				49,
				9,
				0,
				0,
				0,
				0,
				0,
				0,
				127,
				255,
				0,
				0,
				0,
				0,
				0,
				0,
				0,
				127,
				255,
				255,
				255,
				255,
				190,
				124,
				126,
				63,
				223,
				227,
				252,
				126,
				19,
				131,
				129,
				16
			]
		},
		{
			"offset": 136272,
			"bytes": [
				0,
				0,
				0,
				0,
				0,
				0,
				224,
				240,
				0,
				0,
				0,
				0,
				0,
				0,
				0,
				224,
				248,
				252,
				255,
				255,
				255,
				121,
				217,
				207,
				240,
				248,
				252,
				63,
				15,
				183,
				62,
				48,
				0,
				0,
				0,
				0,
				0,
				0,
				0,
				0,
				0,
				0,
				0,
				0,
				0,
				0,
				0,
				0,
				0,
				0,
				192,
				192,
				226,
				130,
				148,
				32,
				0,
				0,
				56,
				254,
				253,
				253,
				107,
				211
			]
		},
		{
			"offset": 143408,
			"bytes": [
				0,
				0,
				0,
				25,
				58,
				57,
				49,
				3,
				3,
				15,
				31,
				22,
				37,
				6,
				15,
				62,
				1,
				7,
				1,
				124,
				254,
				255,
				127,
				1,
				31,
				3,
				7,
				39,
				7,
				2,
				33,
				0,
				0,
				0,
				32,
				16,
				0,
				0,
				232,
				252,
				128,
				224,
				240,
				248,
				248,
				248,
				240,
				232,
				254,
				249,
				249,
				254,
				124,
				248,
				240,
				240,
				108,
				182,
				182,
				180,
				240,
				240,
				224,
				224
			]
		},
		{
			"offset": 143472,
			"bytes": [
				1,
				3,
				7,
				15,
				31,
				14,
				28,
				60,
				0,
				1,
				3,
				7,
				14,
				60,
				56,
				24,
				60,
				12,
				4,
				0,
				16,
				8,
				8,
				0,
				24,
				24,
				30,
				30,
				46,
				118,
				244,
				0,
				248,
				248,
				248,
				240,
				248,
				248,
				124,
				28,
				240,
				240,
				240,
				96,
				112,
				112,
				56,
				56,
				12,
				28,
				4,
				0,
				12,
				2,
				0,
				0,
				62,
				14,
				15,
				15,
				3,
				28,
				60,
				0
			]
		},
		{
			"offset": 143536,
			"bytes": [
				0,
				0,
				0,
				100,
				232,
				228,
				143,
				7,
				14,
				63,
				127,
				91,
				151,
				27,
				127,
				255,
				31,
				31,
				31,
				15,
				63,
				127,
				127,
				63,
				105,
				13,
				14,
				6,
				17,
				3,
				1,
				16,
				0,
				0,
				128,
				64,
				0,
				0,
				128,
				192,
				0,
				128,
				192,
				224,
				224,
				224,
				192,
				128,
				224,
				224,
				16,
				16,
				240,
				224,
				224,
				224,
				192,
				192,
				224,
				224,
				192,
				192,
				0,
				192
			]
		},
		{
			"offset": 143600,
			"bytes": [
				15,
				15,
				31,
				31,
				15,
				7,
				9,
				1,
				7,
				7,
				11,
				11,
				27,
				27,
				7,
				7,
				7,
				1,
				0,
				0,
				1,
				0,
				0,
				0,
				3,
				3,
				1,
				1,
				2,
				7,
				15,
				0,
				224,
				224,
				192,
				128,
				128,
				128,
				128,
				128,
				192,
				192,
				128,
				0,
				0,
				0,
				0,
				0,
				192,
				128,
				128,
				0,
				0,
				128,
				128,
				0,
				128,
				192,
				224,
				240,
				240,
				96,
				64,
				0
			]
		},
		{
			"offset": 143664,
			"bytes": [
				0,
				0,
				0,
				100,
				232,
				228,
				195,
				15,
				14,
				63,
				127,
				91,
				151,
				27,
				63,
				255,
				7,
				31,
				63,
				111,
				159,
				135,
				147,
				99,
				127,
				15,
				15,
				55,
				119,
				115,
				97,
				1,
				0,
				0,
				128,
				64,
				0,
				0,
				176,
				248,
				0,
				128,
				192,
				224,
				224,
				224,
				192,
				240,
				252,
				250,
				241,
				243,
				255,
				255,
				254,
				252,
				120,
				188,
				222,
				206,
				166,
				6,
				0,
				160
			]
		},
		{
			"offset": 143728,
			"bytes": [
				3,
				7,
				7,
				15,
				31,
				31,
				14,
				14,
				1,
				3,
				3,
				7,
				14,
				14,
				60,
				60,
				62,
				62,
				12,
				4,
				16,
				8,
				8,
				0,
				28,
				28,
				30,
				30,
				46,
				118,
				244,
				0,
				252,
				252,
				248,
				248,
				120,
				120,
				120,
				60,
				216,
				248,
				240,
				112,
				48,
				48,
				48,
				24,
				14,
				15,
				14,
				2,
				4,
				2,
				2,
				0,
				60,
				28,
				7,
				7,
				11,
				29,
				61,
				0
			]
		},
		{
			"offset": 143792,
			"bytes": [
				63,
				63,
				255,
				63,
				23,
				37,
				16,
				16,
				65,
				254,
				124,
				241,
				123,
				27,
				111,
				239
			]
		},
		{
			"offset": 143808,
			"bytes": [
				0,
				0,
				0,
				0,
				0,
				0,
				0,
				0,
				0,
				0,
				0,
				0,
				0,
				0,
				0,
				0
			]
		},
		{
			"offset": 143824,
			"bytes": [
				248,
				248,
				252,
				248,
				240,
				248,
				100,
				96,
				240,
				240,
				242,
				231,
				207,
				255,
				251,
				135
			]
		},
		{
			"offset": 143840,
			"bytes": [
				0,
				0,
				0,
				0,
				0,
				0,
				0,
				0,
				0,
				0,
				0,
				0,
				0,
				0,
				0,
				0
			]
		},
		{
			"offset": 143856,
			"bytes": [
				7,
				15,
				31,
				31,
				63,
				62,
				28,
				24,
				3,
				7,
				15,
				14,
				30,
				29,
				121,
				112,
				120,
				60,
				60,
				24,
				8,
				32,
				16,
				16,
				48,
				24,
				24,
				60,
				60,
				30,
				110,
				232
			]
		},
		{
			"offset": 143888,
			"bytes": [
				63,
				63,
				255,
				95,
				8,
				16,
				8,
				8,
				64,
				255,
				127,
				56,
				60,
				14,
				54,
				118,
				0,
				0,
				0,
				0,
				0,
				0,
				0,
				0,
				0,
				0,
				0,
				0,
				0,
				0,
				0,
				0,
				248,
				248,
				248,
				240,
				240,
				248,
				56,
				56,
				240,
				240,
				112,
				96,
				96,
				112,
				240,
				240,
				120,
				124,
				92,
				8,
				0,
				32,
				16,
				16,
				48,
				56,
				56,
				60,
				60,
				30,
				110,
				232
			]
		},
		{
			"offset": 143952,
			"bytes": [
				0,
				0,
				0,
				25,
				58,
				57,
				48,
				1,
				3,
				15,
				31,
				22,
				37,
				6,
				15,
				63,
				111,
				255,
				255,
				255,
				255,
				254,
				252,
				252,
				29,
				93,
				61,
				126,
				124,
				120,
				120,
				248,
				0,
				0,
				32,
				16,
				0,
				0,
				0,
				135,
				128,
				224,
				240,
				248,
				248,
				248,
				240,
				224,
				207,
				239,
				159,
				158,
				222,
				124,
				0,
				0,
				132,
				192,
				225,
				248,
				60,
				0,
				0,
				0
			]
		},
		{
			"offset": 144080,
			"bytes": [
				0,
				0,
				0,
				100,
				232,
				228,
				193,
				7,
				14,
				63,
				127,
				91,
				151,
				27,
				62,
				252,
				15,
				255,
				255,
				254,
				246,
				250,
				252,
				252,
				112,
				97,
				96,
				104,
				108,
				116,
				120,
				248,
				0,
				0,
				128,
				64,
				0,
				0,
				252,
				255,
				0,
				128,
				192,
				224,
				224,
				224,
				0,
				252,
				255,
				3,
				0,
				0,
				0,
				0,
				0,
				0,
				3,
				0,
				0,
				0,
				0,
				0,
				0,
				0
			]
		},
		{
			"offset": 144176,
			"bytes": [
				0,
				0,
				0,
				12,
				29,
				28,
				24,
				31,
				1,
				7,
				15,
				11,
				18,
				3,
				7,
				0,
				63,
				127,
				191,
				23,
				163,
				193,
				129,
				1,
				31,
				61,
				113,
				227,
				193,
				128,
				0,
				0,
				0,
				0,
				16,
				136,
				0,
				128,
				124,
				254,
				192,
				240,
				248,
				124,
				252,
				124,
				128,
				108,
				254,
				251,
				249,
				255,
				254,
				248,
				248,
				248,
				244,
				244,
				246,
				246,
				240,
				240,
				240,
				240
			]
		},
		{
			"offset": 144256,
			"bytes": [
				0,
				0,
				0,
				31,
				63,
				63,
				31,
				0,
				0,
				0,
				0,
				8,
				1,
				0,
				8,
				0
			]
		},
		{
			"offset": 144336,
			"bytes": [
				0,
				0,
				4,
				8,
				0,
				16,
				41,
				3,
				0,
				0,
				30,
				63,
				127,
				111,
				215,
				255,
				115,
				123,
				58,
				4,
				62,
				127,
				127,
				63,
				143,
				71,
				37,
				3,
				19,
				3,
				2,
				17,
				0,
				0,
				0,
				0,
				0,
				48,
				248,
				252,
				0,
				0,
				0,
				0,
				128,
				128,
				16,
				232,
				250,
				250,
				254,
				126,
				122,
				250,
				252,
				240,
				116,
				180,
				180,
				180,
				180,
				116,
				224,
				224
			]
		},
		{
			"offset": 144400,
			"bytes": [
				0,
				0,
				0,
				0,
				0,
				0,
				16,
				32,
				0,
				0,
				0,
				0,
				0,
				28,
				62,
				127,
				1,
				1,
				21,
				9,
				0,
				28,
				30,
				14,
				126,
				254,
				234,
				246,
				127,
				99,
				49,
				9,
				0,
				0,
				0,
				0,
				0,
				0,
				127,
				255,
				0,
				0,
				0,
				0,
				0,
				0,
				0,
				127,
				255,
				255,
				255,
				255,
				190,
				124,
				126,
				63,
				223,
				227,
				252,
				126,
				19,
				131,
				129,
				16
			]
		},
		{
			"offset": 144464,
			"bytes": [
				0,
				0,
				0,
				0,
				0,
				0,
				224,
				240,
				0,
				0,
				0,
				0,
				0,
				0,
				0,
				224,
				248,
				252,
				255,
				255,
				255,
				121,
				217,
				207,
				240,
				248,
				252,
				63,
				15,
				183,
				62,
				48,
				0,
				0,
				0,
				0,
				0,
				0,
				0,
				0,
				0,
				0,
				0,
				0,
				0,
				0,
				0,
				0,
				0,
				0,
				192,
				192,
				226,
				130,
				148,
				32,
				0,
				0,
				56,
				254,
				253,
				253,
				107,
				211
			]
		},
		{
			"offset": 151600,
			"bytes": [
				0,
				0,
				0,
				25,
				58,
				57,
				49,
				3,
				3,
				15,
				31,
				22,
				37,
				6,
				15,
				62,
				1,
				7,
				1,
				124,
				254,
				255,
				127,
				1,
				31,
				3,
				7,
				39,
				7,
				2,
				33,
				0,
				0,
				0,
				32,
				16,
				0,
				0,
				232,
				252,
				128,
				224,
				240,
				248,
				248,
				248,
				240,
				232,
				254,
				249,
				249,
				254,
				124,
				248,
				240,
				240,
				108,
				182,
				182,
				180,
				240,
				240,
				224,
				224
			]
		},
		{
			"offset": 151664,
			"bytes": [
				1,
				3,
				7,
				15,
				31,
				14,
				28,
				60,
				0,
				1,
				3,
				7,
				14,
				60,
				56,
				24,
				60,
				12,
				4,
				0,
				16,
				8,
				8,
				0,
				24,
				24,
				30,
				30,
				46,
				118,
				244,
				0,
				248,
				248,
				248,
				240,
				248,
				248,
				124,
				28,
				240,
				240,
				240,
				96,
				112,
				112,
				56,
				56,
				12,
				28,
				4,
				0,
				12,
				2,
				0,
				0,
				62,
				14,
				15,
				15,
				3,
				28,
				60,
				0
			]
		},
		{
			"offset": 151728,
			"bytes": [
				0,
				0,
				0,
				100,
				232,
				228,
				143,
				7,
				14,
				63,
				127,
				91,
				151,
				27,
				127,
				255,
				31,
				31,
				31,
				15,
				63,
				127,
				127,
				63,
				105,
				13,
				14,
				6,
				17,
				3,
				1,
				16,
				0,
				0,
				128,
				64,
				0,
				0,
				128,
				192,
				0,
				128,
				192,
				224,
				224,
				224,
				192,
				128,
				224,
				224,
				16,
				16,
				240,
				224,
				224,
				224,
				192,
				192,
				224,
				224,
				192,
				192,
				0,
				192
			]
		},
		{
			"offset": 151792,
			"bytes": [
				15,
				15,
				31,
				31,
				15,
				7,
				9,
				1,
				7,
				7,
				11,
				11,
				27,
				27,
				7,
				7,
				7,
				1,
				0,
				0,
				1,
				0,
				0,
				0,
				3,
				3,
				1,
				1,
				2,
				7,
				15,
				0,
				224,
				224,
				192,
				128,
				128,
				128,
				128,
				128,
				192,
				192,
				128,
				0,
				0,
				0,
				0,
				0,
				192,
				128,
				128,
				0,
				0,
				128,
				128,
				0,
				128,
				192,
				224,
				240,
				240,
				96,
				64,
				0
			]
		},
		{
			"offset": 151856,
			"bytes": [
				0,
				0,
				0,
				100,
				232,
				228,
				195,
				15,
				14,
				63,
				127,
				91,
				151,
				27,
				63,
				255,
				7,
				31,
				63,
				111,
				159,
				135,
				147,
				99,
				127,
				15,
				15,
				55,
				119,
				115,
				97,
				1,
				0,
				0,
				128,
				64,
				0,
				0,
				176,
				248,
				0,
				128,
				192,
				224,
				224,
				224,
				192,
				240,
				252,
				250,
				241,
				243,
				255,
				255,
				254,
				252,
				120,
				188,
				222,
				206,
				166,
				6,
				0,
				160
			]
		},
		{
			"offset": 151920,
			"bytes": [
				3,
				7,
				7,
				15,
				31,
				31,
				14,
				14,
				1,
				3,
				3,
				7,
				14,
				14,
				60,
				60,
				62,
				62,
				12,
				4,
				16,
				8,
				8,
				0,
				28,
				28,
				30,
				30,
				46,
				118,
				244,
				0,
				252,
				252,
				248,
				248,
				120,
				120,
				120,
				60,
				216,
				248,
				240,
				112,
				48,
				48,
				48,
				24,
				14,
				15,
				14,
				2,
				4,
				2,
				2,
				0,
				60,
				28,
				7,
				7,
				11,
				29,
				61,
				0
			]
		},
		{
			"offset": 151984,
			"bytes": [
				63,
				63,
				255,
				63,
				23,
				37,
				16,
				16,
				65,
				254,
				124,
				241,
				123,
				27,
				111,
				239
			]
		},
		{
			"offset": 152000,
			"bytes": [
				0,
				0,
				0,
				0,
				0,
				0,
				0,
				0,
				0,
				0,
				0,
				0,
				0,
				0,
				0,
				0
			]
		},
		{
			"offset": 152016,
			"bytes": [
				248,
				248,
				252,
				248,
				240,
				248,
				100,
				96,
				240,
				240,
				242,
				231,
				207,
				255,
				251,
				135
			]
		},
		{
			"offset": 152032,
			"bytes": [
				0,
				0,
				0,
				0,
				0,
				0,
				0,
				0,
				0,
				0,
				0,
				0,
				0,
				0,
				0,
				0
			]
		},
		{
			"offset": 152048,
			"bytes": [
				7,
				15,
				31,
				31,
				63,
				62,
				28,
				24,
				3,
				7,
				15,
				14,
				30,
				29,
				121,
				112,
				120,
				60,
				60,
				24,
				8,
				32,
				16,
				16,
				48,
				24,
				24,
				60,
				60,
				30,
				110,
				232
			]
		},
		{
			"offset": 152080,
			"bytes": [
				63,
				63,
				255,
				95,
				8,
				16,
				8,
				8,
				64,
				255,
				127,
				56,
				60,
				14,
				54,
				118,
				0,
				0,
				0,
				0,
				0,
				0,
				0,
				0,
				0,
				0,
				0,
				0,
				0,
				0,
				0,
				0,
				248,
				248,
				248,
				240,
				240,
				248,
				56,
				56,
				240,
				240,
				112,
				96,
				96,
				112,
				240,
				240,
				120,
				124,
				92,
				8,
				0,
				32,
				16,
				16,
				48,
				56,
				56,
				60,
				60,
				30,
				110,
				232
			]
		},
		{
			"offset": 152144,
			"bytes": [
				0,
				0,
				0,
				25,
				58,
				57,
				48,
				1,
				3,
				15,
				31,
				22,
				37,
				6,
				15,
				63,
				111,
				255,
				255,
				255,
				255,
				254,
				252,
				252,
				29,
				93,
				61,
				126,
				124,
				120,
				120,
				248,
				0,
				0,
				32,
				16,
				0,
				0,
				0,
				135,
				128,
				224,
				240,
				248,
				248,
				248,
				240,
				224,
				207,
				239,
				159,
				158,
				222,
				124,
				0,
				0,
				132,
				192,
				225,
				248,
				60,
				0,
				0,
				0
			]
		},
		{
			"offset": 152272,
			"bytes": [
				0,
				0,
				0,
				100,
				232,
				228,
				193,
				7,
				14,
				63,
				127,
				91,
				151,
				27,
				62,
				252,
				15,
				255,
				255,
				254,
				246,
				250,
				252,
				252,
				112,
				97,
				96,
				104,
				108,
				116,
				120,
				248,
				0,
				0,
				128,
				64,
				0,
				0,
				252,
				255,
				0,
				128,
				192,
				224,
				224,
				224,
				0,
				252,
				255,
				3,
				0,
				0,
				0,
				0,
				0,
				0,
				3,
				0,
				0,
				0,
				0,
				0,
				0,
				0
			]
		},
		{
			"offset": 152368,
			"bytes": [
				0,
				0,
				0,
				12,
				29,
				28,
				24,
				31,
				1,
				7,
				15,
				11,
				18,
				3,
				7,
				0,
				63,
				127,
				191,
				23,
				163,
				193,
				129,
				1,
				31,
				61,
				113,
				227,
				193,
				128,
				0,
				0,
				0,
				0,
				16,
				136,
				0,
				128,
				124,
				254,
				192,
				240,
				248,
				124,
				252,
				124,
				128,
				108,
				254,
				251,
				249,
				255,
				254,
				248,
				248,
				248,
				244,
				244,
				246,
				246,
				240,
				240,
				240,
				240
			]
		},
		{
			"offset": 152448,
			"bytes": [
				0,
				0,
				0,
				31,
				63,
				63,
				31,
				0,
				0,
				0,
				0,
				8,
				1,
				0,
				8,
				0
			]
		},
		{
			"offset": 152528,
			"bytes": [
				0,
				0,
				4,
				8,
				0,
				16,
				41,
				3,
				0,
				0,
				30,
				63,
				127,
				111,
				215,
				255,
				115,
				123,
				58,
				4,
				62,
				127,
				127,
				63,
				143,
				71,
				37,
				3,
				19,
				3,
				2,
				17,
				0,
				0,
				0,
				0,
				0,
				48,
				248,
				252,
				0,
				0,
				0,
				0,
				128,
				128,
				16,
				232,
				250,
				250,
				254,
				126,
				122,
				250,
				252,
				240,
				116,
				180,
				180,
				180,
				180,
				116,
				224,
				224
			]
		},
		{
			"offset": 152592,
			"bytes": [
				0,
				0,
				0,
				0,
				0,
				0,
				16,
				32,
				0,
				0,
				0,
				0,
				0,
				28,
				62,
				127,
				1,
				1,
				21,
				9,
				0,
				28,
				30,
				14,
				126,
				254,
				234,
				246,
				127,
				99,
				49,
				9,
				0,
				0,
				0,
				0,
				0,
				0,
				127,
				255,
				0,
				0,
				0,
				0,
				0,
				0,
				0,
				127,
				255,
				255,
				255,
				255,
				190,
				124,
				126,
				63,
				223,
				227,
				252,
				126,
				19,
				131,
				129,
				16
			]
		},
		{
			"offset": 152656,
			"bytes": [
				0,
				0,
				0,
				0,
				0,
				0,
				224,
				240,
				0,
				0,
				0,
				0,
				0,
				0,
				0,
				224,
				248,
				252,
				255,
				255,
				255,
				121,
				217,
				207,
				240,
				248,
				252,
				63,
				15,
				183,
				62,
				48,
				0,
				0,
				0,
				0,
				0,
				0,
				0,
				0,
				0,
				0,
				0,
				0,
				0,
				0,
				0,
				0,
				0,
				0,
				192,
				192,
				226,
				130,
				148,
				32,
				0,
				0,
				56,
				254,
				253,
				253,
				107,
				211
			]
		},
		{
			"offset": 159792,
			"bytes": [
				0,
				0,
				0,
				25,
				58,
				57,
				49,
				3,
				3,
				15,
				31,
				22,
				37,
				6,
				15,
				62,
				1,
				7,
				1,
				124,
				254,
				255,
				127,
				1,
				31,
				3,
				7,
				39,
				7,
				2,
				33,
				0,
				0,
				0,
				32,
				16,
				0,
				0,
				232,
				252,
				128,
				224,
				240,
				248,
				248,
				248,
				240,
				232,
				254,
				249,
				249,
				254,
				124,
				248,
				240,
				240,
				108,
				182,
				182,
				180,
				240,
				240,
				224,
				224
			]
		},
		{
			"offset": 159856,
			"bytes": [
				1,
				3,
				7,
				15,
				31,
				14,
				28,
				60,
				0,
				1,
				3,
				7,
				14,
				60,
				56,
				24,
				60,
				12,
				4,
				0,
				16,
				8,
				8,
				0,
				24,
				24,
				30,
				30,
				46,
				118,
				244,
				0,
				248,
				248,
				248,
				240,
				248,
				248,
				124,
				28,
				240,
				240,
				240,
				96,
				112,
				112,
				56,
				56,
				12,
				28,
				4,
				0,
				12,
				2,
				0,
				0,
				62,
				14,
				15,
				15,
				3,
				28,
				60,
				0
			]
		},
		{
			"offset": 159920,
			"bytes": [
				0,
				0,
				0,
				100,
				232,
				228,
				143,
				7,
				14,
				63,
				127,
				91,
				151,
				27,
				127,
				255,
				31,
				31,
				31,
				15,
				63,
				127,
				127,
				63,
				105,
				13,
				14,
				6,
				17,
				3,
				1,
				16,
				0,
				0,
				128,
				64,
				0,
				0,
				128,
				192,
				0,
				128,
				192,
				224,
				224,
				224,
				192,
				128,
				224,
				224,
				16,
				16,
				240,
				224,
				224,
				224,
				192,
				192,
				224,
				224,
				192,
				192,
				0,
				192
			]
		},
		{
			"offset": 159984,
			"bytes": [
				15,
				15,
				31,
				31,
				15,
				7,
				9,
				1,
				7,
				7,
				11,
				11,
				27,
				27,
				7,
				7,
				7,
				1,
				0,
				0,
				1,
				0,
				0,
				0,
				3,
				3,
				1,
				1,
				2,
				7,
				15,
				0,
				224,
				224,
				192,
				128,
				128,
				128,
				128,
				128,
				192,
				192,
				128,
				0,
				0,
				0,
				0,
				0,
				192,
				128,
				128,
				0,
				0,
				128,
				128,
				0,
				128,
				192,
				224,
				240,
				240,
				96,
				64,
				0
			]
		},
		{
			"offset": 160048,
			"bytes": [
				0,
				0,
				0,
				100,
				232,
				228,
				195,
				15,
				14,
				63,
				127,
				91,
				151,
				27,
				63,
				255,
				7,
				31,
				63,
				111,
				159,
				135,
				147,
				99,
				127,
				15,
				15,
				55,
				119,
				115,
				97,
				1,
				0,
				0,
				128,
				64,
				0,
				0,
				176,
				248,
				0,
				128,
				192,
				224,
				224,
				224,
				192,
				240,
				252,
				250,
				241,
				243,
				255,
				255,
				254,
				252,
				120,
				188,
				222,
				206,
				166,
				6,
				0,
				160
			]
		},
		{
			"offset": 160112,
			"bytes": [
				3,
				7,
				7,
				15,
				31,
				31,
				14,
				14,
				1,
				3,
				3,
				7,
				14,
				14,
				60,
				60,
				62,
				62,
				12,
				4,
				16,
				8,
				8,
				0,
				28,
				28,
				30,
				30,
				46,
				118,
				244,
				0,
				252,
				252,
				248,
				248,
				120,
				120,
				120,
				60,
				216,
				248,
				240,
				112,
				48,
				48,
				48,
				24,
				14,
				15,
				14,
				2,
				4,
				2,
				2,
				0,
				60,
				28,
				7,
				7,
				11,
				29,
				61,
				0
			]
		},
		{
			"offset": 160176,
			"bytes": [
				63,
				63,
				255,
				63,
				23,
				37,
				16,
				16,
				65,
				254,
				124,
				241,
				123,
				27,
				111,
				239
			]
		},
		{
			"offset": 160192,
			"bytes": [
				0,
				0,
				0,
				0,
				0,
				0,
				0,
				0,
				0,
				0,
				0,
				0,
				0,
				0,
				0,
				0
			]
		},
		{
			"offset": 160208,
			"bytes": [
				248,
				248,
				252,
				248,
				240,
				248,
				100,
				96,
				240,
				240,
				242,
				231,
				207,
				255,
				251,
				135
			]
		},
		{
			"offset": 160224,
			"bytes": [
				0,
				0,
				0,
				0,
				0,
				0,
				0,
				0,
				0,
				0,
				0,
				0,
				0,
				0,
				0,
				0
			]
		},
		{
			"offset": 160240,
			"bytes": [
				7,
				15,
				31,
				31,
				63,
				62,
				28,
				24,
				3,
				7,
				15,
				14,
				30,
				29,
				121,
				112,
				120,
				60,
				60,
				24,
				8,
				32,
				16,
				16,
				48,
				24,
				24,
				60,
				60,
				30,
				110,
				232
			]
		},
		{
			"offset": 160272,
			"bytes": [
				63,
				63,
				255,
				95,
				8,
				16,
				8,
				8,
				64,
				255,
				127,
				56,
				60,
				14,
				54,
				118,
				0,
				0,
				0,
				0,
				0,
				0,
				0,
				0,
				0,
				0,
				0,
				0,
				0,
				0,
				0,
				0,
				248,
				248,
				248,
				240,
				240,
				248,
				56,
				56,
				240,
				240,
				112,
				96,
				96,
				112,
				240,
				240,
				120,
				124,
				92,
				8,
				0,
				32,
				16,
				16,
				48,
				56,
				56,
				60,
				60,
				30,
				110,
				232
			]
		},
		{
			"offset": 160336,
			"bytes": [
				0,
				0,
				0,
				25,
				58,
				57,
				48,
				1,
				3,
				15,
				31,
				22,
				37,
				6,
				15,
				63,
				111,
				255,
				255,
				255,
				255,
				254,
				252,
				252,
				29,
				93,
				61,
				126,
				124,
				120,
				120,
				248,
				0,
				0,
				32,
				16,
				0,
				0,
				0,
				135,
				128,
				224,
				240,
				248,
				248,
				248,
				240,
				224,
				207,
				239,
				159,
				158,
				222,
				124,
				0,
				0,
				132,
				192,
				225,
				248,
				60,
				0,
				0,
				0
			]
		},
		{
			"offset": 160464,
			"bytes": [
				0,
				0,
				0,
				100,
				232,
				228,
				193,
				7,
				14,
				63,
				127,
				91,
				151,
				27,
				62,
				252,
				15,
				255,
				255,
				254,
				246,
				250,
				252,
				252,
				112,
				97,
				96,
				104,
				108,
				116,
				120,
				248,
				0,
				0,
				128,
				64,
				0,
				0,
				252,
				255,
				0,
				128,
				192,
				224,
				224,
				224,
				0,
				252,
				255,
				3,
				0,
				0,
				0,
				0,
				0,
				0,
				3,
				0,
				0,
				0,
				0,
				0,
				0,
				0
			]
		},
		{
			"offset": 160560,
			"bytes": [
				0,
				0,
				0,
				12,
				29,
				28,
				24,
				31,
				1,
				7,
				15,
				11,
				18,
				3,
				7,
				0,
				63,
				127,
				191,
				23,
				163,
				193,
				129,
				1,
				31,
				61,
				113,
				227,
				193,
				128,
				0,
				0,
				0,
				0,
				16,
				136,
				0,
				128,
				124,
				254,
				192,
				240,
				248,
				124,
				252,
				124,
				128,
				108,
				254,
				251,
				249,
				255,
				254,
				248,
				248,
				248,
				244,
				244,
				246,
				246,
				240,
				240,
				240,
				240
			]
		},
		{
			"offset": 160640,
			"bytes": [
				0,
				0,
				0,
				31,
				63,
				63,
				31,
				0,
				0,
				0,
				0,
				8,
				1,
				0,
				8,
				0
			]
		},
		{
			"offset": 160720,
			"bytes": [
				0,
				0,
				4,
				8,
				0,
				16,
				41,
				3,
				0,
				0,
				30,
				63,
				127,
				111,
				215,
				255,
				115,
				123,
				58,
				4,
				62,
				127,
				127,
				63,
				143,
				71,
				37,
				3,
				19,
				3,
				2,
				17,
				0,
				0,
				0,
				0,
				0,
				48,
				248,
				252,
				0,
				0,
				0,
				0,
				128,
				128,
				16,
				232,
				250,
				250,
				254,
				126,
				122,
				250,
				252,
				240,
				116,
				180,
				180,
				180,
				180,
				116,
				224,
				224
			]
		},
		{
			"offset": 160784,
			"bytes": [
				0,
				0,
				0,
				0,
				0,
				0,
				16,
				32,
				0,
				0,
				0,
				0,
				0,
				28,
				62,
				127,
				1,
				1,
				21,
				9,
				0,
				28,
				30,
				14,
				126,
				254,
				234,
				246,
				127,
				99,
				49,
				9,
				0,
				0,
				0,
				0,
				0,
				0,
				127,
				255,
				0,
				0,
				0,
				0,
				0,
				0,
				0,
				127,
				255,
				255,
				255,
				255,
				190,
				124,
				126,
				63,
				223,
				227,
				252,
				126,
				19,
				131,
				129,
				16
			]
		},
		{
			"offset": 160848,
			"bytes": [
				0,
				0,
				0,
				0,
				0,
				0,
				224,
				240,
				0,
				0,
				0,
				0,
				0,
				0,
				0,
				224,
				248,
				252,
				255,
				255,
				255,
				121,
				217,
				207,
				240,
				248,
				252,
				63,
				15,
				183,
				62,
				48,
				0,
				0,
				0,
				0,
				0,
				0,
				0,
				0,
				0,
				0,
				0,
				0,
				0,
				0,
				0,
				0,
				0,
				0,
				192,
				192,
				226,
				130,
				148,
				32,
				0,
				0,
				56,
				254,
				253,
				253,
				107,
				211
			]
		},
		{
			"offset": 167984,
			"bytes": [
				0,
				0,
				0,
				25,
				58,
				57,
				49,
				3,
				3,
				15,
				31,
				22,
				37,
				6,
				15,
				62,
				1,
				7,
				1,
				124,
				254,
				255,
				127,
				1,
				31,
				3,
				7,
				39,
				7,
				2,
				33,
				0,
				0,
				0,
				32,
				16,
				0,
				0,
				232,
				252,
				128,
				224,
				240,
				248,
				248,
				248,
				240,
				232,
				254,
				249,
				249,
				254,
				124,
				248,
				240,
				240,
				108,
				182,
				182,
				180,
				240,
				240,
				224,
				224
			]
		},
		{
			"offset": 168048,
			"bytes": [
				1,
				3,
				7,
				15,
				31,
				14,
				28,
				60,
				0,
				1,
				3,
				7,
				14,
				60,
				56,
				24,
				60,
				12,
				4,
				0,
				16,
				8,
				8,
				0,
				24,
				24,
				30,
				30,
				46,
				118,
				244,
				0,
				248,
				248,
				248,
				240,
				248,
				248,
				124,
				28,
				240,
				240,
				240,
				96,
				112,
				112,
				56,
				56,
				12,
				28,
				4,
				0,
				12,
				2,
				0,
				0,
				62,
				14,
				15,
				15,
				3,
				28,
				60,
				0
			]
		},
		{
			"offset": 168112,
			"bytes": [
				0,
				0,
				0,
				100,
				232,
				228,
				143,
				7,
				14,
				63,
				127,
				91,
				151,
				27,
				127,
				255,
				31,
				31,
				31,
				15,
				63,
				127,
				127,
				63,
				105,
				13,
				14,
				6,
				17,
				3,
				1,
				16,
				0,
				0,
				128,
				64,
				0,
				0,
				128,
				192,
				0,
				128,
				192,
				224,
				224,
				224,
				192,
				128,
				224,
				224,
				16,
				16,
				240,
				224,
				224,
				224,
				192,
				192,
				224,
				224,
				192,
				192,
				0,
				192
			]
		},
		{
			"offset": 168176,
			"bytes": [
				15,
				15,
				31,
				31,
				15,
				7,
				9,
				1,
				7,
				7,
				11,
				11,
				27,
				27,
				7,
				7,
				7,
				1,
				0,
				0,
				1,
				0,
				0,
				0,
				3,
				3,
				1,
				1,
				2,
				7,
				15,
				0,
				224,
				224,
				192,
				128,
				128,
				128,
				128,
				128,
				192,
				192,
				128,
				0,
				0,
				0,
				0,
				0,
				192,
				128,
				128,
				0,
				0,
				128,
				128,
				0,
				128,
				192,
				224,
				240,
				240,
				96,
				64,
				0
			]
		},
		{
			"offset": 168240,
			"bytes": [
				0,
				0,
				0,
				100,
				232,
				228,
				195,
				15,
				14,
				63,
				127,
				91,
				151,
				27,
				63,
				255,
				7,
				31,
				63,
				111,
				159,
				135,
				147,
				99,
				127,
				15,
				15,
				55,
				119,
				115,
				97,
				1,
				0,
				0,
				128,
				64,
				0,
				0,
				176,
				248,
				0,
				128,
				192,
				224,
				224,
				224,
				192,
				240,
				252,
				250,
				241,
				243,
				255,
				255,
				254,
				252,
				120,
				188,
				222,
				206,
				166,
				6,
				0,
				160
			]
		},
		{
			"offset": 168304,
			"bytes": [
				3,
				7,
				7,
				15,
				31,
				31,
				14,
				14,
				1,
				3,
				3,
				7,
				14,
				14,
				60,
				60,
				62,
				62,
				12,
				4,
				16,
				8,
				8,
				0,
				28,
				28,
				30,
				30,
				46,
				118,
				244,
				0,
				252,
				252,
				248,
				248,
				120,
				120,
				120,
				60,
				216,
				248,
				240,
				112,
				48,
				48,
				48,
				24,
				14,
				15,
				14,
				2,
				4,
				2,
				2,
				0,
				60,
				28,
				7,
				7,
				11,
				29,
				61,
				0
			]
		},
		{
			"offset": 168368,
			"bytes": [
				63,
				63,
				255,
				63,
				23,
				37,
				16,
				16,
				65,
				254,
				124,
				241,
				123,
				27,
				111,
				239
			]
		},
		{
			"offset": 168384,
			"bytes": [
				0,
				0,
				0,
				0,
				0,
				0,
				0,
				0,
				0,
				0,
				0,
				0,
				0,
				0,
				0,
				0
			]
		},
		{
			"offset": 168400,
			"bytes": [
				248,
				248,
				252,
				248,
				240,
				248,
				100,
				96,
				240,
				240,
				242,
				231,
				207,
				255,
				251,
				135
			]
		},
		{
			"offset": 168416,
			"bytes": [
				0,
				0,
				0,
				0,
				0,
				0,
				0,
				0,
				0,
				0,
				0,
				0,
				0,
				0,
				0,
				0
			]
		},
		{
			"offset": 168432,
			"bytes": [
				7,
				15,
				31,
				31,
				63,
				62,
				28,
				24,
				3,
				7,
				15,
				14,
				30,
				29,
				121,
				112,
				120,
				60,
				60,
				24,
				8,
				32,
				16,
				16,
				48,
				24,
				24,
				60,
				60,
				30,
				110,
				232
			]
		},
		{
			"offset": 168464,
			"bytes": [
				63,
				63,
				255,
				95,
				8,
				16,
				8,
				8,
				64,
				255,
				127,
				56,
				60,
				14,
				54,
				118,
				0,
				0,
				0,
				0,
				0,
				0,
				0,
				0,
				0,
				0,
				0,
				0,
				0,
				0,
				0,
				0,
				248,
				248,
				248,
				240,
				240,
				248,
				56,
				56,
				240,
				240,
				112,
				96,
				96,
				112,
				240,
				240,
				120,
				124,
				92,
				8,
				0,
				32,
				16,
				16,
				48,
				56,
				56,
				60,
				60,
				30,
				110,
				232
			]
		},
		{
			"offset": 168528,
			"bytes": [
				0,
				0,
				0,
				25,
				58,
				57,
				48,
				1,
				3,
				15,
				31,
				22,
				37,
				6,
				15,
				63,
				111,
				255,
				255,
				255,
				255,
				254,
				252,
				252,
				29,
				93,
				61,
				126,
				124,
				120,
				120,
				248,
				0,
				0,
				32,
				16,
				0,
				0,
				0,
				135,
				128,
				224,
				240,
				248,
				248,
				248,
				240,
				224,
				207,
				239,
				159,
				158,
				222,
				124,
				0,
				0,
				132,
				192,
				225,
				248,
				60,
				0,
				0,
				0
			]
		},
		{
			"offset": 168656,
			"bytes": [
				0,
				0,
				0,
				100,
				232,
				228,
				193,
				7,
				14,
				63,
				127,
				91,
				151,
				27,
				62,
				252,
				15,
				255,
				255,
				254,
				246,
				250,
				252,
				252,
				112,
				97,
				96,
				104,
				108,
				116,
				120,
				248,
				0,
				0,
				128,
				64,
				0,
				0,
				252,
				255,
				0,
				128,
				192,
				224,
				224,
				224,
				0,
				252,
				255,
				3,
				0,
				0,
				0,
				0,
				0,
				0,
				3,
				0,
				0,
				0,
				0,
				0,
				0,
				0
			]
		},
		{
			"offset": 168752,
			"bytes": [
				0,
				0,
				0,
				12,
				29,
				28,
				24,
				31,
				1,
				7,
				15,
				11,
				18,
				3,
				7,
				0,
				63,
				127,
				191,
				23,
				163,
				193,
				129,
				1,
				31,
				61,
				113,
				227,
				193,
				128,
				0,
				0,
				0,
				0,
				16,
				136,
				0,
				128,
				124,
				254,
				192,
				240,
				248,
				124,
				252,
				124,
				128,
				108,
				254,
				251,
				249,
				255,
				254,
				248,
				248,
				248,
				244,
				244,
				246,
				246,
				240,
				240,
				240,
				240
			]
		},
		{
			"offset": 168832,
			"bytes": [
				0,
				0,
				0,
				31,
				63,
				63,
				31,
				0,
				0,
				0,
				0,
				8,
				1,
				0,
				8,
				0
			]
		},
		{
			"offset": 168912,
			"bytes": [
				0,
				0,
				4,
				8,
				0,
				16,
				41,
				3,
				0,
				0,
				30,
				63,
				127,
				111,
				215,
				255,
				115,
				123,
				58,
				4,
				62,
				127,
				127,
				63,
				143,
				71,
				37,
				3,
				19,
				3,
				2,
				17,
				0,
				0,
				0,
				0,
				0,
				48,
				248,
				252,
				0,
				0,
				0,
				0,
				128,
				128,
				16,
				232,
				250,
				250,
				254,
				126,
				122,
				250,
				252,
				240,
				116,
				180,
				180,
				180,
				180,
				116,
				224,
				224
			]
		},
		{
			"offset": 168976,
			"bytes": [
				0,
				0,
				0,
				0,
				0,
				0,
				16,
				32,
				0,
				0,
				0,
				0,
				0,
				28,
				62,
				127,
				1,
				1,
				21,
				9,
				0,
				28,
				30,
				14,
				126,
				254,
				234,
				246,
				127,
				99,
				49,
				9,
				0,
				0,
				0,
				0,
				0,
				0,
				127,
				255,
				0,
				0,
				0,
				0,
				0,
				0,
				0,
				127,
				255,
				255,
				255,
				255,
				190,
				124,
				126,
				63,
				223,
				227,
				252,
				126,
				19,
				131,
				129,
				16
			]
		},
		{
			"offset": 169040,
			"bytes": [
				0,
				0,
				0,
				0,
				0,
				0,
				224,
				240,
				0,
				0,
				0,
				0,
				0,
				0,
				0,
				224,
				248,
				252,
				255,
				255,
				255,
				121,
				217,
				207,
				240,
				248,
				252,
				63,
				15,
				183,
				62,
				48,
				0,
				0,
				0,
				0,
				0,
				0,
				0,
				0,
				0,
				0,
				0,
				0,
				0,
				0,
				0,
				0,
				0,
				0,
				192,
				192,
				226,
				130,
				148,
				32,
				0,
				0,
				56,
				254,
				253,
				253,
				107,
				211
			]
		},
		{
			"offset": 172080,
			"bytes": [
				0,
				0,
				0,
				25,
				58,
				57,
				49,
				3,
				3,
				15,
				31,
				22,
				37,
				6,
				15,
				62,
				1,
				7,
				1,
				124,
				254,
				255,
				127,
				1,
				31,
				3,
				7,
				39,
				7,
				2,
				33,
				0,
				0,
				0,
				32,
				16,
				0,
				0,
				232,
				252,
				128,
				224,
				240,
				248,
				248,
				248,
				240,
				232,
				254,
				249,
				249,
				254,
				124,
				248,
				240,
				240,
				108,
				182,
				182,
				180,
				240,
				240,
				224,
				224
			]
		},
		{
			"offset": 172144,
			"bytes": [
				1,
				3,
				7,
				15,
				31,
				14,
				28,
				60,
				0,
				1,
				3,
				7,
				14,
				60,
				56,
				24,
				60,
				12,
				4,
				0,
				16,
				8,
				8,
				0,
				24,
				24,
				30,
				30,
				46,
				118,
				244,
				0,
				248,
				248,
				248,
				240,
				248,
				248,
				124,
				28,
				240,
				240,
				240,
				96,
				112,
				112,
				56,
				56,
				12,
				28,
				4,
				0,
				12,
				2,
				0,
				0,
				62,
				14,
				15,
				15,
				3,
				28,
				60,
				0
			]
		},
		{
			"offset": 172208,
			"bytes": [
				0,
				0,
				0,
				100,
				232,
				228,
				143,
				7,
				14,
				63,
				127,
				91,
				151,
				27,
				127,
				255,
				31,
				31,
				31,
				15,
				63,
				127,
				127,
				63,
				105,
				13,
				14,
				6,
				17,
				3,
				1,
				16,
				0,
				0,
				128,
				64,
				0,
				0,
				128,
				192,
				0,
				128,
				192,
				224,
				224,
				224,
				192,
				128,
				224,
				224,
				16,
				16,
				240,
				224,
				224,
				224,
				192,
				192,
				224,
				224,
				192,
				192,
				0,
				192
			]
		},
		{
			"offset": 172272,
			"bytes": [
				15,
				15,
				31,
				31,
				15,
				7,
				9,
				1,
				7,
				7,
				11,
				11,
				27,
				27,
				7,
				7,
				7,
				1,
				0,
				0,
				1,
				0,
				0,
				0,
				3,
				3,
				1,
				1,
				2,
				7,
				15,
				0,
				224,
				224,
				192,
				128,
				128,
				128,
				128,
				128,
				192,
				192,
				128,
				0,
				0,
				0,
				0,
				0,
				192,
				128,
				128,
				0,
				0,
				128,
				128,
				0,
				128,
				192,
				224,
				240,
				240,
				96,
				64,
				0
			]
		},
		{
			"offset": 172336,
			"bytes": [
				0,
				0,
				0,
				100,
				232,
				228,
				195,
				15,
				14,
				63,
				127,
				91,
				151,
				27,
				63,
				255,
				7,
				31,
				63,
				111,
				159,
				135,
				147,
				99,
				127,
				15,
				15,
				55,
				119,
				115,
				97,
				1,
				0,
				0,
				128,
				64,
				0,
				0,
				176,
				248,
				0,
				128,
				192,
				224,
				224,
				224,
				192,
				240,
				252,
				250,
				241,
				243,
				255,
				255,
				254,
				252,
				120,
				188,
				222,
				206,
				166,
				6,
				0,
				160
			]
		},
		{
			"offset": 172400,
			"bytes": [
				3,
				7,
				7,
				15,
				31,
				31,
				14,
				14,
				1,
				3,
				3,
				7,
				14,
				14,
				60,
				60,
				62,
				62,
				12,
				4,
				16,
				8,
				8,
				0,
				28,
				28,
				30,
				30,
				46,
				118,
				244,
				0,
				252,
				252,
				248,
				248,
				120,
				120,
				120,
				60,
				216,
				248,
				240,
				112,
				48,
				48,
				48,
				24,
				14,
				15,
				14,
				2,
				4,
				2,
				2,
				0,
				60,
				28,
				7,
				7,
				11,
				29,
				61,
				0
			]
		},
		{
			"offset": 172464,
			"bytes": [
				63,
				63,
				255,
				63,
				23,
				37,
				16,
				16,
				65,
				254,
				124,
				241,
				123,
				27,
				111,
				239
			]
		},
		{
			"offset": 172480,
			"bytes": [
				0,
				0,
				0,
				0,
				0,
				0,
				0,
				0,
				0,
				0,
				0,
				0,
				0,
				0,
				0,
				0
			]
		},
		{
			"offset": 172496,
			"bytes": [
				248,
				248,
				252,
				248,
				240,
				248,
				100,
				96,
				240,
				240,
				242,
				231,
				207,
				255,
				251,
				135
			]
		},
		{
			"offset": 172512,
			"bytes": [
				0,
				0,
				0,
				0,
				0,
				0,
				0,
				0,
				0,
				0,
				0,
				0,
				0,
				0,
				0,
				0
			]
		},
		{
			"offset": 172528,
			"bytes": [
				7,
				15,
				31,
				31,
				63,
				62,
				28,
				24,
				3,
				7,
				15,
				14,
				30,
				29,
				121,
				112,
				120,
				60,
				60,
				24,
				8,
				32,
				16,
				16,
				48,
				24,
				24,
				60,
				60,
				30,
				110,
				232
			]
		},
		{
			"offset": 172560,
			"bytes": [
				63,
				63,
				255,
				95,
				8,
				16,
				8,
				8,
				64,
				255,
				127,
				56,
				60,
				14,
				54,
				118,
				0,
				0,
				0,
				0,
				0,
				0,
				0,
				0,
				0,
				0,
				0,
				0,
				0,
				0,
				0,
				0,
				248,
				248,
				248,
				240,
				240,
				248,
				56,
				56,
				240,
				240,
				112,
				96,
				96,
				112,
				240,
				240,
				120,
				124,
				92,
				8,
				0,
				32,
				16,
				16,
				48,
				56,
				56,
				60,
				60,
				30,
				110,
				232
			]
		},
		{
			"offset": 172624,
			"bytes": [
				0,
				0,
				0,
				25,
				58,
				57,
				48,
				1,
				3,
				15,
				31,
				22,
				37,
				6,
				15,
				63,
				111,
				255,
				255,
				255,
				255,
				254,
				252,
				252,
				29,
				93,
				61,
				126,
				124,
				120,
				120,
				248,
				0,
				0,
				32,
				16,
				0,
				0,
				0,
				135,
				128,
				224,
				240,
				248,
				248,
				248,
				240,
				224,
				207,
				239,
				159,
				158,
				222,
				124,
				0,
				0,
				132,
				192,
				225,
				248,
				60,
				0,
				0,
				0
			]
		},
		{
			"offset": 172752,
			"bytes": [
				0,
				0,
				0,
				100,
				232,
				228,
				193,
				7,
				14,
				63,
				127,
				91,
				151,
				27,
				62,
				252,
				15,
				255,
				255,
				254,
				246,
				250,
				252,
				252,
				112,
				97,
				96,
				104,
				108,
				116,
				120,
				248,
				0,
				0,
				128,
				64,
				0,
				0,
				252,
				255,
				0,
				128,
				192,
				224,
				224,
				224,
				0,
				252,
				255,
				3,
				0,
				0,
				0,
				0,
				0,
				0,
				3,
				0,
				0,
				0,
				0,
				0,
				0,
				0
			]
		},
		{
			"offset": 172848,
			"bytes": [
				0,
				0,
				0,
				12,
				29,
				28,
				24,
				31,
				1,
				7,
				15,
				11,
				18,
				3,
				7,
				0,
				63,
				127,
				191,
				23,
				163,
				193,
				129,
				1,
				31,
				61,
				113,
				227,
				193,
				128,
				0,
				0,
				0,
				0,
				16,
				136,
				0,
				128,
				124,
				254,
				192,
				240,
				248,
				124,
				252,
				124,
				128,
				108,
				254,
				251,
				249,
				255,
				254,
				248,
				248,
				248,
				244,
				244,
				246,
				246,
				240,
				240,
				240,
				240
			]
		},
		{
			"offset": 172928,
			"bytes": [
				0,
				0,
				0,
				31,
				63,
				63,
				31,
				0,
				0,
				0,
				0,
				8,
				1,
				0,
				8,
				0
			]
		},
		{
			"offset": 173008,
			"bytes": [
				0,
				0,
				4,
				8,
				0,
				16,
				41,
				3,
				0,
				0,
				30,
				63,
				127,
				111,
				215,
				255,
				115,
				123,
				58,
				4,
				62,
				127,
				127,
				63,
				143,
				71,
				37,
				3,
				19,
				3,
				2,
				17,
				0,
				0,
				0,
				0,
				0,
				48,
				248,
				252,
				0,
				0,
				0,
				0,
				128,
				128,
				16,
				232,
				250,
				250,
				254,
				126,
				122,
				250,
				252,
				240,
				116,
				180,
				180,
				180,
				180,
				116,
				224,
				224
			]
		},
		{
			"offset": 173072,
			"bytes": [
				0,
				0,
				0,
				0,
				0,
				0,
				16,
				32,
				0,
				0,
				0,
				0,
				0,
				28,
				62,
				127,
				1,
				1,
				21,
				9,
				0,
				28,
				30,
				14,
				126,
				254,
				234,
				246,
				127,
				99,
				49,
				9,
				0,
				0,
				0,
				0,
				0,
				0,
				127,
				255,
				0,
				0,
				0,
				0,
				0,
				0,
				0,
				127,
				255,
				255,
				255,
				255,
				190,
				124,
				126,
				63,
				223,
				227,
				252,
				126,
				19,
				131,
				129,
				16
			]
		},
		{
			"offset": 173136,
			"bytes": [
				0,
				0,
				0,
				0,
				0,
				0,
				224,
				240,
				0,
				0,
				0,
				0,
				0,
				0,
				0,
				224,
				248,
				252,
				255,
				255,
				255,
				121,
				217,
				207,
				240,
				248,
				252,
				63,
				15,
				183,
				62,
				48,
				0,
				0,
				0,
				0,
				0,
				0,
				0,
				0,
				0,
				0,
				0,
				0,
				0,
				0,
				0,
				0,
				0,
				0,
				192,
				192,
				226,
				130,
				148,
				32,
				0,
				0,
				56,
				254,
				253,
				253,
				107,
				211
			]
		},
		{
			"offset": 180272,
			"bytes": [
				0,
				0,
				0,
				25,
				58,
				57,
				49,
				3,
				3,
				15,
				31,
				22,
				37,
				6,
				15,
				62,
				1,
				7,
				1,
				124,
				254,
				255,
				127,
				1,
				31,
				3,
				7,
				39,
				7,
				2,
				33,
				0,
				0,
				0,
				32,
				16,
				0,
				0,
				232,
				252,
				128,
				224,
				240,
				248,
				248,
				248,
				240,
				232,
				254,
				249,
				249,
				254,
				124,
				248,
				240,
				240,
				108,
				182,
				182,
				180,
				240,
				240,
				224,
				224
			]
		},
		{
			"offset": 180336,
			"bytes": [
				1,
				3,
				7,
				15,
				31,
				14,
				28,
				60,
				0,
				1,
				3,
				7,
				14,
				60,
				56,
				24,
				60,
				12,
				4,
				0,
				16,
				8,
				8,
				0,
				24,
				24,
				30,
				30,
				46,
				118,
				244,
				0,
				248,
				248,
				248,
				240,
				248,
				248,
				124,
				28,
				240,
				240,
				240,
				96,
				112,
				112,
				56,
				56,
				12,
				28,
				4,
				0,
				12,
				2,
				0,
				0,
				62,
				14,
				15,
				15,
				3,
				28,
				60,
				0
			]
		},
		{
			"offset": 180400,
			"bytes": [
				0,
				0,
				0,
				100,
				232,
				228,
				143,
				7,
				14,
				63,
				127,
				91,
				151,
				27,
				127,
				255,
				31,
				31,
				31,
				15,
				63,
				127,
				127,
				63,
				105,
				13,
				14,
				6,
				17,
				3,
				1,
				16,
				0,
				0,
				128,
				64,
				0,
				0,
				128,
				192,
				0,
				128,
				192,
				224,
				224,
				224,
				192,
				128,
				224,
				224,
				16,
				16,
				240,
				224,
				224,
				224,
				192,
				192,
				224,
				224,
				192,
				192,
				0,
				192
			]
		},
		{
			"offset": 180464,
			"bytes": [
				15,
				15,
				31,
				31,
				15,
				7,
				9,
				1,
				7,
				7,
				11,
				11,
				27,
				27,
				7,
				7,
				7,
				1,
				0,
				0,
				1,
				0,
				0,
				0,
				3,
				3,
				1,
				1,
				2,
				7,
				15,
				0,
				224,
				224,
				192,
				128,
				128,
				128,
				128,
				128,
				192,
				192,
				128,
				0,
				0,
				0,
				0,
				0,
				192,
				128,
				128,
				0,
				0,
				128,
				128,
				0,
				128,
				192,
				224,
				240,
				240,
				96,
				64,
				0
			]
		},
		{
			"offset": 180528,
			"bytes": [
				0,
				0,
				0,
				100,
				232,
				228,
				195,
				15,
				14,
				63,
				127,
				91,
				151,
				27,
				63,
				255,
				7,
				31,
				63,
				111,
				159,
				135,
				147,
				99,
				127,
				15,
				15,
				55,
				119,
				115,
				97,
				1,
				0,
				0,
				128,
				64,
				0,
				0,
				176,
				248,
				0,
				128,
				192,
				224,
				224,
				224,
				192,
				240,
				252,
				250,
				241,
				243,
				255,
				255,
				254,
				252,
				120,
				188,
				222,
				206,
				166,
				6,
				0,
				160
			]
		},
		{
			"offset": 180592,
			"bytes": [
				3,
				7,
				7,
				15,
				31,
				31,
				14,
				14,
				1,
				3,
				3,
				7,
				14,
				14,
				60,
				60,
				62,
				62,
				12,
				4,
				16,
				8,
				8,
				0,
				28,
				28,
				30,
				30,
				46,
				118,
				244,
				0,
				252,
				252,
				248,
				248,
				120,
				120,
				120,
				60,
				216,
				248,
				240,
				112,
				48,
				48,
				48,
				24,
				14,
				15,
				14,
				2,
				4,
				2,
				2,
				0,
				60,
				28,
				7,
				7,
				11,
				29,
				61,
				0
			]
		},
		{
			"offset": 180656,
			"bytes": [
				63,
				63,
				255,
				63,
				23,
				37,
				16,
				16,
				65,
				254,
				124,
				241,
				123,
				27,
				111,
				239
			]
		},
		{
			"offset": 180672,
			"bytes": [
				0,
				0,
				0,
				0,
				0,
				0,
				0,
				0,
				0,
				0,
				0,
				0,
				0,
				0,
				0,
				0
			]
		},
		{
			"offset": 180688,
			"bytes": [
				248,
				248,
				252,
				248,
				240,
				248,
				100,
				96,
				240,
				240,
				242,
				231,
				207,
				255,
				251,
				135
			]
		},
		{
			"offset": 180704,
			"bytes": [
				0,
				0,
				0,
				0,
				0,
				0,
				0,
				0,
				0,
				0,
				0,
				0,
				0,
				0,
				0,
				0
			]
		},
		{
			"offset": 180720,
			"bytes": [
				7,
				15,
				31,
				31,
				63,
				62,
				28,
				24,
				3,
				7,
				15,
				14,
				30,
				29,
				121,
				112,
				120,
				60,
				60,
				24,
				8,
				32,
				16,
				16,
				48,
				24,
				24,
				60,
				60,
				30,
				110,
				232
			]
		},
		{
			"offset": 180752,
			"bytes": [
				63,
				63,
				255,
				95,
				8,
				16,
				8,
				8,
				64,
				255,
				127,
				56,
				60,
				14,
				54,
				118,
				0,
				0,
				0,
				0,
				0,
				0,
				0,
				0,
				0,
				0,
				0,
				0,
				0,
				0,
				0,
				0,
				248,
				248,
				248,
				240,
				240,
				248,
				56,
				56,
				240,
				240,
				112,
				96,
				96,
				112,
				240,
				240,
				120,
				124,
				92,
				8,
				0,
				32,
				16,
				16,
				48,
				56,
				56,
				60,
				60,
				30,
				110,
				232
			]
		},
		{
			"offset": 180816,
			"bytes": [
				0,
				0,
				0,
				25,
				58,
				57,
				48,
				1,
				3,
				15,
				31,
				22,
				37,
				6,
				15,
				63,
				111,
				255,
				255,
				255,
				255,
				254,
				252,
				252,
				29,
				93,
				61,
				126,
				124,
				120,
				120,
				248,
				0,
				0,
				32,
				16,
				0,
				0,
				0,
				135,
				128,
				224,
				240,
				248,
				248,
				248,
				240,
				224,
				207,
				239,
				159,
				158,
				222,
				124,
				0,
				0,
				132,
				192,
				225,
				248,
				60,
				0,
				0,
				0
			]
		},
		{
			"offset": 180944,
			"bytes": [
				0,
				0,
				0,
				100,
				232,
				228,
				193,
				7,
				14,
				63,
				127,
				91,
				151,
				27,
				62,
				252,
				15,
				255,
				255,
				254,
				246,
				250,
				252,
				252,
				112,
				97,
				96,
				104,
				108,
				116,
				120,
				248,
				0,
				0,
				128,
				64,
				0,
				0,
				252,
				255,
				0,
				128,
				192,
				224,
				224,
				224,
				0,
				252,
				255,
				3,
				0,
				0,
				0,
				0,
				0,
				0,
				3,
				0,
				0,
				0,
				0,
				0,
				0,
				0
			]
		},
		{
			"offset": 181040,
			"bytes": [
				0,
				0,
				0,
				12,
				29,
				28,
				24,
				31,
				1,
				7,
				15,
				11,
				18,
				3,
				7,
				0,
				63,
				127,
				191,
				23,
				163,
				193,
				129,
				1,
				31,
				61,
				113,
				227,
				193,
				128,
				0,
				0,
				0,
				0,
				16,
				136,
				0,
				128,
				124,
				254,
				192,
				240,
				248,
				124,
				252,
				124,
				128,
				108,
				254,
				251,
				249,
				255,
				254,
				248,
				248,
				248,
				244,
				244,
				246,
				246,
				240,
				240,
				240,
				240
			]
		},
		{
			"offset": 181120,
			"bytes": [
				0,
				0,
				0,
				31,
				63,
				63,
				31,
				0,
				0,
				0,
				0,
				8,
				1,
				0,
				8,
				0
			]
		},
		{
			"offset": 181200,
			"bytes": [
				0,
				0,
				4,
				8,
				0,
				16,
				41,
				3,
				0,
				0,
				30,
				63,
				127,
				111,
				215,
				255,
				115,
				123,
				58,
				4,
				62,
				127,
				127,
				63,
				143,
				71,
				37,
				3,
				19,
				3,
				2,
				17,
				0,
				0,
				0,
				0,
				0,
				48,
				248,
				252,
				0,
				0,
				0,
				0,
				128,
				128,
				16,
				232,
				250,
				250,
				254,
				126,
				122,
				250,
				252,
				240,
				116,
				180,
				180,
				180,
				180,
				116,
				224,
				224
			]
		},
		{
			"offset": 181264,
			"bytes": [
				0,
				0,
				0,
				0,
				0,
				0,
				16,
				32,
				0,
				0,
				0,
				0,
				0,
				28,
				62,
				127,
				1,
				1,
				21,
				9,
				0,
				28,
				30,
				14,
				126,
				254,
				234,
				246,
				127,
				99,
				49,
				9,
				0,
				0,
				0,
				0,
				0,
				0,
				127,
				255,
				0,
				0,
				0,
				0,
				0,
				0,
				0,
				127,
				255,
				255,
				255,
				255,
				190,
				124,
				126,
				63,
				223,
				227,
				252,
				126,
				19,
				131,
				129,
				16
			]
		},
		{
			"offset": 181328,
			"bytes": [
				0,
				0,
				0,
				0,
				0,
				0,
				224,
				240,
				0,
				0,
				0,
				0,
				0,
				0,
				0,
				224,
				248,
				252,
				255,
				255,
				255,
				121,
				217,
				207,
				240,
				248,
				252,
				63,
				15,
				183,
				62,
				48,
				0,
				0,
				0,
				0,
				0,
				0,
				0,
				0,
				0,
				0,
				0,
				0,
				0,
				0,
				0,
				0,
				0,
				0,
				192,
				192,
				226,
				130,
				148,
				32,
				0,
				0,
				56,
				254,
				253,
				253,
				107,
				211
			]
		},
		{
			"offset": 229424,
			"bytes": [
				0,
				0,
				0,
				25,
				58,
				57,
				49,
				3,
				3,
				15,
				31,
				22,
				37,
				6,
				15,
				62,
				1,
				7,
				1,
				124,
				254,
				255,
				127,
				1,
				31,
				3,
				7,
				39,
				7,
				2,
				33,
				0,
				0,
				0,
				32,
				16,
				0,
				0,
				232,
				252,
				128,
				224,
				240,
				248,
				248,
				248,
				240,
				232,
				254,
				249,
				249,
				254,
				124,
				248,
				240,
				240,
				108,
				182,
				182,
				180,
				240,
				240,
				224,
				224
			]
		},
		{
			"offset": 229488,
			"bytes": [
				1,
				3,
				7,
				15,
				31,
				14,
				28,
				60,
				0,
				1,
				3,
				7,
				14,
				60,
				56,
				24,
				60,
				12,
				4,
				0,
				16,
				8,
				8,
				0,
				24,
				24,
				30,
				30,
				46,
				118,
				244,
				0,
				248,
				248,
				248,
				240,
				248,
				248,
				124,
				28,
				240,
				240,
				240,
				96,
				112,
				112,
				56,
				56,
				12,
				28,
				4,
				0,
				12,
				2,
				0,
				0,
				62,
				14,
				15,
				15,
				3,
				28,
				60,
				0
			]
		},
		{
			"offset": 229552,
			"bytes": [
				0,
				0,
				0,
				100,
				232,
				228,
				143,
				7,
				14,
				63,
				127,
				91,
				151,
				27,
				127,
				255,
				31,
				31,
				31,
				15,
				63,
				127,
				127,
				63,
				105,
				13,
				14,
				6,
				17,
				3,
				1,
				16,
				0,
				0,
				128,
				64,
				0,
				0,
				128,
				192,
				0,
				128,
				192,
				224,
				224,
				224,
				192,
				128,
				224,
				224,
				16,
				16,
				240,
				224,
				224,
				224,
				192,
				192,
				224,
				224,
				192,
				192,
				0,
				192
			]
		},
		{
			"offset": 229616,
			"bytes": [
				15,
				15,
				31,
				31,
				15,
				7,
				9,
				1,
				7,
				7,
				11,
				11,
				27,
				27,
				7,
				7,
				7,
				1,
				0,
				0,
				1,
				0,
				0,
				0,
				3,
				3,
				1,
				1,
				2,
				7,
				15,
				0,
				224,
				224,
				192,
				128,
				128,
				128,
				128,
				128,
				192,
				192,
				128,
				0,
				0,
				0,
				0,
				0,
				192,
				128,
				128,
				0,
				0,
				128,
				128,
				0,
				128,
				192,
				224,
				240,
				240,
				96,
				64,
				0
			]
		},
		{
			"offset": 229680,
			"bytes": [
				0,
				0,
				0,
				100,
				232,
				228,
				195,
				15,
				14,
				63,
				127,
				91,
				151,
				27,
				63,
				255,
				7,
				31,
				63,
				111,
				159,
				135,
				147,
				99,
				127,
				15,
				15,
				55,
				119,
				115,
				97,
				1,
				0,
				0,
				128,
				64,
				0,
				0,
				176,
				248,
				0,
				128,
				192,
				224,
				224,
				224,
				192,
				240,
				252,
				250,
				241,
				243,
				255,
				255,
				254,
				252,
				120,
				188,
				222,
				206,
				166,
				6,
				0,
				160
			]
		},
		{
			"offset": 229744,
			"bytes": [
				3,
				7,
				7,
				15,
				31,
				31,
				14,
				14,
				1,
				3,
				3,
				7,
				14,
				14,
				60,
				60,
				62,
				62,
				12,
				4,
				16,
				8,
				8,
				0,
				28,
				28,
				30,
				30,
				46,
				118,
				244,
				0,
				252,
				252,
				248,
				248,
				120,
				120,
				120,
				60,
				216,
				248,
				240,
				112,
				48,
				48,
				48,
				24,
				14,
				15,
				14,
				2,
				4,
				2,
				2,
				0,
				60,
				28,
				7,
				7,
				11,
				29,
				61,
				0
			]
		},
		{
			"offset": 229808,
			"bytes": [
				63,
				63,
				255,
				63,
				23,
				37,
				16,
				16,
				65,
				254,
				124,
				241,
				123,
				27,
				111,
				239
			]
		},
		{
			"offset": 229824,
			"bytes": [
				0,
				0,
				0,
				0,
				0,
				0,
				0,
				0,
				0,
				0,
				0,
				0,
				0,
				0,
				0,
				0
			]
		},
		{
			"offset": 229840,
			"bytes": [
				248,
				248,
				252,
				248,
				240,
				248,
				100,
				96,
				240,
				240,
				242,
				231,
				207,
				255,
				251,
				135
			]
		},
		{
			"offset": 229856,
			"bytes": [
				0,
				0,
				0,
				0,
				0,
				0,
				0,
				0,
				0,
				0,
				0,
				0,
				0,
				0,
				0,
				0
			]
		},
		{
			"offset": 229872,
			"bytes": [
				7,
				15,
				31,
				31,
				63,
				62,
				28,
				24,
				3,
				7,
				15,
				14,
				30,
				29,
				121,
				112,
				120,
				60,
				60,
				24,
				8,
				32,
				16,
				16,
				48,
				24,
				24,
				60,
				60,
				30,
				110,
				232
			]
		},
		{
			"offset": 229904,
			"bytes": [
				63,
				63,
				255,
				95,
				8,
				16,
				8,
				8,
				64,
				255,
				127,
				56,
				60,
				14,
				54,
				118,
				0,
				0,
				0,
				0,
				0,
				0,
				0,
				0,
				0,
				0,
				0,
				0,
				0,
				0,
				0,
				0,
				248,
				248,
				248,
				240,
				240,
				248,
				56,
				56,
				240,
				240,
				112,
				96,
				96,
				112,
				240,
				240,
				120,
				124,
				92,
				8,
				0,
				32,
				16,
				16,
				48,
				56,
				56,
				60,
				60,
				30,
				110,
				232
			]
		},
		{
			"offset": 229968,
			"bytes": [
				0,
				0,
				0,
				25,
				58,
				57,
				48,
				1,
				3,
				15,
				31,
				22,
				37,
				6,
				15,
				63,
				111,
				255,
				255,
				255,
				255,
				254,
				252,
				252,
				29,
				93,
				61,
				126,
				124,
				120,
				120,
				248,
				0,
				0,
				32,
				16,
				0,
				0,
				0,
				135,
				128,
				224,
				240,
				248,
				248,
				248,
				240,
				224,
				207,
				239,
				159,
				158,
				222,
				124,
				0,
				0,
				132,
				192,
				225,
				248,
				60,
				0,
				0,
				0
			]
		},
		{
			"offset": 230096,
			"bytes": [
				0,
				0,
				0,
				100,
				232,
				228,
				193,
				7,
				14,
				63,
				127,
				91,
				151,
				27,
				62,
				252,
				15,
				255,
				255,
				254,
				246,
				250,
				252,
				252,
				112,
				97,
				96,
				104,
				108,
				116,
				120,
				248,
				0,
				0,
				128,
				64,
				0,
				0,
				252,
				255,
				0,
				128,
				192,
				224,
				224,
				224,
				0,
				252,
				255,
				3,
				0,
				0,
				0,
				0,
				0,
				0,
				3,
				0,
				0,
				0,
				0,
				0,
				0,
				0
			]
		},
		{
			"offset": 230192,
			"bytes": [
				0,
				0,
				0,
				12,
				29,
				28,
				24,
				31,
				1,
				7,
				15,
				11,
				18,
				3,
				7,
				0,
				63,
				127,
				191,
				23,
				163,
				193,
				129,
				1,
				31,
				61,
				113,
				227,
				193,
				128,
				0,
				0,
				0,
				0,
				16,
				136,
				0,
				128,
				124,
				254,
				192,
				240,
				248,
				124,
				252,
				124,
				128,
				108,
				254,
				251,
				249,
				255,
				254,
				248,
				248,
				248,
				244,
				244,
				246,
				246,
				240,
				240,
				240,
				240
			]
		},
		{
			"offset": 230272,
			"bytes": [
				0,
				0,
				0,
				31,
				63,
				63,
				31,
				0,
				0,
				0,
				0,
				8,
				1,
				0,
				8,
				0
			]
		},
		{
			"offset": 230352,
			"bytes": [
				0,
				0,
				4,
				8,
				0,
				16,
				41,
				3,
				0,
				0,
				30,
				63,
				127,
				111,
				215,
				255,
				115,
				123,
				58,
				4,
				62,
				127,
				127,
				63,
				143,
				71,
				37,
				3,
				19,
				3,
				2,
				17,
				0,
				0,
				0,
				0,
				0,
				48,
				248,
				252,
				0,
				0,
				0,
				0,
				128,
				128,
				16,
				232,
				250,
				250,
				254,
				126,
				122,
				250,
				252,
				240,
				116,
				180,
				180,
				180,
				180,
				116,
				224,
				224
			]
		},
		{
			"offset": 230416,
			"bytes": [
				0,
				0,
				0,
				0,
				0,
				0,
				16,
				32,
				0,
				0,
				0,
				0,
				0,
				28,
				62,
				127,
				1,
				1,
				21,
				9,
				0,
				28,
				30,
				14,
				126,
				254,
				234,
				246,
				127,
				99,
				49,
				9,
				0,
				0,
				0,
				0,
				0,
				0,
				127,
				255,
				0,
				0,
				0,
				0,
				0,
				0,
				0,
				127,
				255,
				255,
				255,
				255,
				190,
				124,
				126,
				63,
				223,
				227,
				252,
				126,
				19,
				131,
				129,
				16
			]
		},
		{
			"offset": 230480,
			"bytes": [
				0,
				0,
				0,
				0,
				0,
				0,
				224,
				240,
				0,
				0,
				0,
				0,
				0,
				0,
				0,
				224,
				248,
				252,
				255,
				255,
				255,
				121,
				217,
				207,
				240,
				248,
				252,
				63,
				15,
				183,
				62,
				48,
				0,
				0,
				0,
				0,
				0,
				0,
				0,
				0,
				0,
				0,
				0,
				0,
				0,
				0,
				0,
				0,
				0,
				0,
				192,
				192,
				226,
				130,
				148,
				32,
				0,
				0,
				56,
				254,
				253,
				253,
				107,
				211
			]
		},
		{
			"offset": 117439,
			"bytes": [
				11,
				22,
				40
			]
		}
	]
}